psgtray/__init__.py
psgtray/psgtray.py
psgtray_foss-1.0.2.dist-info/LICENSE
psgtray_foss-1.0.2.dist-info/METADATA
psgtray_foss-1.0.2.dist-info/WHEEL
psgtray_foss-1.0.2.dist-info/top_level.txt
psgtray_foss-1.0.2.dist-info/RECORD
