Metadata-Version: 2.1
Name: psgtray-foss
Version: 1.0.2
Summary: Mirror of psgtray that depends on  System Tray Icon that works with the PySimpleGUI tkinter port.  Uses pystray to supply the system tray.  Works well under Windows.
Home-page: https://github.com/csm10495/psgtray
Author: WAS: PySimpleGUI
Author-email: WAS: mike@PySimpleGUI.org
Keywords: GUI UI PySimpleGUI tkinter systemtray pystray
Classifier: Programming Language :: Python :: 3
Classifier: Programming Language :: Python :: 3.4
Classifier: Programming Language :: Python :: 3.5
Classifier: Programming Language :: Python :: 3.6
Classifier: Programming Language :: Python :: 3.7
Classifier: Programming Language :: Python :: 3.8
Classifier: Programming Language :: Python :: 3.9
Classifier: Programming Language :: Python :: 3.10
Classifier: License :: OSI Approved :: GNU Lesser General Public License v3 or later (LGPLv3+)
Classifier: Topic :: Multimedia :: Graphics
Classifier: Operating System :: OS Independent
License-File: LICENSE
Requires-Dist: PySimpleGUI-4-foss
Requires-Dist: pystray (<=0.18.0)
Requires-Dist: pillow
